odoo/addons/pos_check_session_state/README.rst
odoo/addons/pos_check_session_state/__init__.py
odoo/addons/pos_check_session_state/__manifest__.py
odoo/addons/pos_check_session_state/i18n/fr.po
odoo/addons/pos_check_session_state/i18n/it.po
odoo/addons/pos_check_session_state/i18n/pos_check_session_state.pot
odoo/addons/pos_check_session_state/models/__init__.py
odoo/addons/pos_check_session_state/models/pos_config.py
odoo/addons/pos_check_session_state/models/pos_order.py
odoo/addons/pos_check_session_state/readme/CONFIGURE.rst
odoo/addons/pos_check_session_state/readme/CONTRIBUTORS.rst
odoo/addons/pos_check_session_state/readme/DESCRIPTION.rst
odoo/addons/pos_check_session_state/static/description/create_from_ui_error.png
odoo/addons/pos_check_session_state/static/description/error_message.png
odoo/addons/pos_check_session_state/static/description/icon.png
odoo/addons/pos_check_session_state/static/description/index.html
odoo/addons/pos_check_session_state/static/description/pos_config_form.png
odoo/addons/pos_check_session_state/static/src/js/chrome.js
odoo/addons/pos_check_session_state/views/templates.xml
odoo/addons/pos_check_session_state/views/view_pos_config.xml
odoo12_addon_pos_check_session_state-12.0.1.0.0.99.dev8.dist-info/METADATA
odoo12_addon_pos_check_session_state-12.0.1.0.0.99.dev8.dist-info/WHEEL
odoo12_addon_pos_check_session_state-12.0.1.0.0.99.dev8.dist-info/top_level.txt
odoo12_addon_pos_check_session_state-12.0.1.0.0.99.dev8.dist-info/RECORD
